[{"2d_box": {"xmin": 694.265381, "ymin": 873.557068, "xmax": 1004.3530890000001, "ymax": 1080.0}, "pid": "0091", "cid": "0"}, {"2d_box": {"xmin": 33.996841, "ymin": 467.847321, "xmax": 353.319229, "ymax": 602.113099}, "pid": "0092", "cid": "0"}, {"2d_box": {"xmin": 315.56604, "ymin": 810.691223, "xmax": 695.634827, "ymax": 1080.0}, "pid": "0098", "cid": "0"}, {"2d_box": {"xmin": 0.0, "ymin": 280.93158, "xmax": 44.588142, "ymax": 344.73465}, "pid": "0095", "cid": "0"}, {"2d_box": {"xmin": 0.0, "ymin": 349.495758, "xmax": 115.243134, "ymax": 433.09368900000004}, "pid": "0094", "cid": "0"}, {"2d_box": {"xmin": 1880.95752, "ymin": 402.084564, "xmax": 1920.0, "ymax": 471.16625999999997}, "pid": "0099", "cid": "0"}]