[{"2d_box": {"xmin": 0.0, "ymin": 358.519745, "xmax": 23.498682, "ymax": 419.437134}, "pid": "0092", "cid": "0"}, {"2d_box": {"xmin": 948.093201, "ymin": 388.185638, "xmax": 1215.689942, "ymax": 490.10110399999996}, "pid": "0093", "cid": "0"}, {"2d_box": {"xmin": 0.0, "ymin": 373.874603, "xmax": 51.73085, "ymax": 429.565765}, "pid": "0091", "cid": "0"}, {"2d_box": {"xmin": 301.155243, "ymin": 810.209839, "xmax": 695.974609, "ymax": 1080.0}, "pid": "0094", "cid": "0"}, {"2d_box": {"xmin": 848.711365, "ymin": 447.24295, "xmax": 1148.886109, "ymax": 565.424926}, "pid": "0090", "cid": "0"}, {"2d_box": {"xmin": 0.0, "ymin": 478.138916, "xmax": 307.890198, "ymax": 660.147461}, "pid": "0099", "cid": "0"}]